chromolog/__init__.py
chromolog/chromolog.py
chromolog-0.2.5.dist-info/licenses/LICENSE
chromolog-0.2.5.dist-info/METADATA
chromolog-0.2.5.dist-info/WHEEL
chromolog-0.2.5.dist-info/top_level.txt
chromolog-0.2.5.dist-info/RECORD
