Metadata-Version: 2.4
Name: chromolog
Version: 0.2.5
Summary: Un micromódulo para imprimir mensajes por consola con texto de color según la dinámica (error, success, warning, information, exception)
Author-email: dev2forge <support@dev2forge.software>
Maintainer-email: tutosrive <tutosrive@dev2forge.software>
License-Expression: MIT
Project-URL: Homepage, https://docs.dev2forge.software/chromolog/
Project-URL: Repository, https://github.com/Dev2Forge/chromolog/
Project-URL: YouTube, https://www.youtube.com/@dev2forge/
Keywords: chromolog,colorama,console,logging,dev2forge,log
Classifier: Programming Language :: Python
Classifier: Programming Language :: Python :: 3.8
Classifier: Programming Language :: Python :: 3.9
Classifier: Programming Language :: Python :: 3.10
Classifier: Programming Language :: Python :: 3.11
Classifier: Programming Language :: Python :: 3.12
Classifier: Programming Language :: Python :: 3.13
Classifier: Programming Language :: Python :: 3.14
Classifier: Operating System :: OS Independent
Classifier: Intended Audience :: Developers
Classifier: Topic :: Software Development :: Libraries
Classifier: Topic :: Utilities
Classifier: Environment :: Console
Classifier: Development Status :: 5 - Production/Stable
Requires-Python: >=3.8
License-File: LICENSE
Requires-Dist: colorama==0.4.6
Dynamic: license-file
